conceal/__init__.py
conceal/collage.py
conceal/colorshift.py
conceal/config.py
conceal/dither.py
conceal/noise.py
conceal/normalize.py
conceal/palette.py
conceal/runner.py
conceal/voronoi.py
conceal-1.0.0.dist-info/METADATA
conceal-1.0.0.dist-info/WHEEL
conceal-1.0.0.dist-info/top_level.txt
conceal-1.0.0.dist-info/RECORD
