Metadata-Version: 2.1
Name: conceal
Version: 1.0.0
Summary: conceal is a camouflage generator.
Home-page: https://github.com/michaelpeterswa/conceal
Author: Michael Peters
Author-email: michaelpeterswa@icloud.com
License: MIT
Platform: UNKNOWN
Classifier: Programming Language :: Python :: 3
Classifier: License :: OSI Approved :: MIT License
Classifier: Operating System :: OS Independent
Requires-Python: >=3.5
